lectio/__init__.py
lectio/exceptions.py
lectio/lectio.py
lectio/helpers/__init__.py
lectio/helpers/schedule.py
lectio/models/__init__.py
lectio/models/school.py
lectio/models/user.py
lectio.py-0.2.1.dist-info/LICENSE
lectio.py-0.2.1.dist-info/METADATA
lectio.py-0.2.1.dist-info/WHEEL
lectio.py-0.2.1.dist-info/top_level.txt
lectio.py-0.2.1.dist-info/RECORD
