Metadata-Version: 2.1
Name: lectio.py
Version: 0.2.1
Summary: Interact with lectio through python
Home-page: https://github.com/dnorhoj/lectio.py
Author: dnorhoj
Author-email: daniel.norhoj@gmail.com
License: UNKNOWN
Platform: UNKNOWN
Classifier: Programming Language :: Python :: 3
Classifier: License :: OSI Approved :: GNU General Public License v3 (GPLv3)
Classifier: Operating System :: OS Independent
License-File: LICENSE
